bb_pbf_html_writer/__init__.py
bb_pbf_html_writer/add_links_to_html.py
bb_pbf_html_writer/create_html.py
bb_pbf_html_writer-0.1.1.dist-info/METADATA
bb_pbf_html_writer-0.1.1.dist-info/WHEEL
bb_pbf_html_writer-0.1.1.dist-info/top_level.txt
bb_pbf_html_writer-0.1.1.dist-info/RECORD
