Metadata-Version: 2.1
Name: bb-pbf-html-writer
Version: 0.1.1
Summary: Writes BB Mega PBF HTML file and adds links to the HTML file.
Author: John Nastala
Author-email: your.email@example.com
Requires-Dist: beautifulsoup4==4.12.3
Requires-Dist: Jinja2==3.1.4
Requires-Dist: MarkupSafe==2.1.5
Requires-Dist: soupsieve==2.6
